jukedj
