Metadata-Version: 1.1
Name: jukedj
Version: 2.0.2
Summary: Django app for models used in the JukeboxPipeline.
Home-page: https://github.com/JukeboxPipeline/jukedj
Author: David Zuber
Author-email: zuber.david@gmx.de
License: BSD
Keywords: jukedj
Platform: UNKNOWN
Classifier: Development Status :: 2 - Pre-Alpha
Classifier: Intended Audience :: Developers
Classifier: License :: OSI Approved :: BSD License
Classifier: Natural Language :: English
Classifier: Programming Language :: Python :: 2.7
